distributed_computing/__init__.py
distributed_computing/api.py
distributed_computing/client.py
distributed_computing/common.py
distributed_computing/globals.py
distributed_computing/server.py
distributed_computing/test.py
distributed_computing-0.2.0.data/scripts/start_node
distributed_computing-0.2.0.dist-info/LICENSE
distributed_computing-0.2.0.dist-info/METADATA
distributed_computing-0.2.0.dist-info/WHEEL
distributed_computing-0.2.0.dist-info/top_level.txt
distributed_computing-0.2.0.dist-info/RECORD
